theoddsapi/__init__.py
theoddsapi/api.py
theoddsapi-1.3.7.dist-info/METADATA
theoddsapi-1.3.7.dist-info/WHEEL
theoddsapi-1.3.7.dist-info/licenses/LICENSE
theoddsapi-1.3.7.dist-info/RECORD
