Metadata-Version: 2.1
Name: theoddsapi
Version: 1.3.7
Summary: A Python wrapper around The Odds-Api V4
Project-URL: Homepage, https://github.com/MidpriceDog/the-odds-api-client
Project-URL: Bug Tracker, https://github.com/MidpriceDog/the-odds-api-client/issues
Author: MidpriceDog
License-File: LICENSE
Classifier: License :: OSI Approved :: MIT License
Classifier: Operating System :: OS Independent
Classifier: Programming Language :: Python :: 3
Requires-Python: >=3.7
